awmproxy/Awm.py
awmproxy/Exceptions.py
awmproxy/__init__.py
awmproxy-0.1.0.dist-info/LICENSE
awmproxy-0.1.0.dist-info/METADATA
awmproxy-0.1.0.dist-info/WHEEL
awmproxy-0.1.0.dist-info/top_level.txt
awmproxy-0.1.0.dist-info/RECORD
