Metadata-Version: 2.1
Name: awmproxy
Version: 0.1.0
Summary: Wrapper for the awmproxy.net api
Home-page: https://github.com/jimtje/awmproxy
Author: jim zhou
Author-email: jimtje@gmail.com
License: MIT
Platform: UNKNOWN
Classifier: License :: OSI Approved :: MIT License
Classifier: Programming Language :: Python
Classifier: Programming Language :: Python :: 3
Classifier: Programming Language :: Python :: 3.6
Classifier: Programming Language :: Python :: Implementation :: CPython
Classifier: Programming Language :: Python :: Implementation :: PyPy
Requires-Python: >=2.6.0
Requires-Dist: requests
